setup.py
pilot_cli/__init__.py
pilot_cli/base.py
pilot_cli/cli.py
pilot_cli/clients.py
pilot_cli/environments.old.py
pilot_cli/environments.py
pilot_cli/extra_environments.py
pilot_cli/servers.py
pilot_cli/utils.py
pilot_cli.egg-info/PKG-INFO
pilot_cli.egg-info/SOURCES.txt
pilot_cli.egg-info/dependency_links.txt
pilot_cli.egg-info/entry_points.txt
pilot_cli.egg-info/requires.txt
pilot_cli.egg-info/top_level.txt